xontrib/avox.py
xontrib_avox-0.8.dist-info/LICENSE
xontrib_avox-0.8.dist-info/METADATA
xontrib_avox-0.8.dist-info/WHEEL
xontrib_avox-0.8.dist-info/top_level.txt
xontrib_avox-0.8.dist-info/RECORD
