Metadata-Version: 2.1
Name: xontrib-avox
Version: 0.8
Summary: Automatic voxes for projects
Home-page: https://github.com/astronouth7303/xontrib-avox
Author: Jamie Bliss
Author-email: astronouth7303@gmail.com
License: GPLv3
Platform: any
Classifier: Environment :: Console
Classifier: Intended Audience :: End Users/Desktop
Classifier: Operating System :: OS Independent
Classifier: Programming Language :: Python
Classifier: Topic :: Desktop Environment
Classifier: Topic :: System :: Shells
Classifier: Topic :: System :: System Shells
